transpa/__init__.py
transpa/eval_util.py
transpa/model.py
transpa/util.py
transpa/version.py
transpa-0.1.1.dist-info/LICENSE
transpa-0.1.1.dist-info/METADATA
transpa-0.1.1.dist-info/WHEEL
transpa-0.1.1.dist-info/top_level.txt
transpa-0.1.1.dist-info/RECORD
