Metadata-Version: 2.1
Name: transpa
Version: 0.1.1
Summary: Translation-based imputation and cell type deconvolution
Home-page: https://github.com/qiaochen/tranSpa
Author: Chen Qiao
Author-email: cqiao@connect.hku.hk
License-File: LICENSE
Requires-Dist: numpy
Requires-Dist: scipy
Requires-Dist: pandas
Requires-Dist: matplotlib
Requires-Dist: tqdm
Requires-Dist: torchmetrics
Requires-Dist: anndata (>=0.7.4)
Requires-Dist: scanpy (>=1.5.1)
Requires-Dist: torch (>=1.13.0)
Requires-Dist: umap-learn (>=0.5.3)
Requires-Dist: torchvision (>=0.14.0)
Requires-Dist: torchaudio
Requires-Dist: scikit-learn
Requires-Dist: squidpy
